nicha/__init__.py
nicha/admin.py
nicha/apps.py
nicha/helpers.py
nicha/models.py
nicha/serializers.py
nicha/tests.py
nicha/urls.py
nicha/views.py
nicha/templates/nicha/account.html
nicha/templates/nicha/change_password.html
nicha/templates/nicha/community.html
nicha/templates/nicha/explore.html
nicha/templates/nicha/faq.html
nicha/templates/nicha/how_it_works.html
nicha/templates/nicha/index.html
nicha/templates/nicha/mobile.html
nicha/templates/nicha/password_reset.html
nicha/templates/nicha/privacy.html
nicha/templates/nicha/sign_in.html
nicha/templates/nicha/terms.html
django_nicha-0.1.dist-info/LICENSE.txt
django_nicha-0.1.dist-info/METADATA
django_nicha-0.1.dist-info/WHEEL
django_nicha-0.1.dist-info/top_level.txt
django_nicha-0.1.dist-info/RECORD
